cellfinder_core/__init__.py
cellfinder_core/main.py
cellfinder_core/types.py
cellfinder_core/classify/__init__.py
cellfinder_core/classify/augment.py
cellfinder_core/classify/classify.py
cellfinder_core/classify/cube_generator.py
cellfinder_core/classify/resnet.py
cellfinder_core/classify/tools.py
cellfinder_core/config/__init__.py
cellfinder_core/config/cellfinder.conf
cellfinder_core/detect/__init__.py
cellfinder_core/detect/detect.py
cellfinder_core/detect/filters/__init__.py
cellfinder_core/detect/filters/setup_filters.py
cellfinder_core/detect/filters/plane/__init__.py
cellfinder_core/detect/filters/plane/classical_filter.py
cellfinder_core/detect/filters/plane/plane_filter.py
cellfinder_core/detect/filters/plane/tile_walker.py
cellfinder_core/detect/filters/volume/__init__.py
cellfinder_core/detect/filters/volume/ball_filter.py
cellfinder_core/detect/filters/volume/structure_detection.py
cellfinder_core/detect/filters/volume/structure_splitting.py
cellfinder_core/detect/filters/volume/volume_filter.py
cellfinder_core/download/__init__.py
cellfinder_core/download/cli.py
cellfinder_core/download/download.py
cellfinder_core/download/models.py
cellfinder_core/tools/IO.py
cellfinder_core/tools/__init__.py
cellfinder_core/tools/array_operations.py
cellfinder_core/tools/geometry.py
cellfinder_core/tools/image_processing.py
cellfinder_core/tools/prep.py
cellfinder_core/tools/source_files.py
cellfinder_core/tools/system.py
cellfinder_core/tools/tf.py
cellfinder_core/tools/tiff.py
cellfinder_core/tools/tools.py
cellfinder_core/train/__init__.py
cellfinder_core/train/train_yml.py
cellfinder_core-1.0.0.dist-info/LICENSE
cellfinder_core-1.0.0.dist-info/METADATA
cellfinder_core-1.0.0.dist-info/WHEEL
cellfinder_core-1.0.0.dist-info/entry_points.txt
cellfinder_core-1.0.0.dist-info/top_level.txt
cellfinder_core-1.0.0.dist-info/RECORD
