Metadata-Version: 2.1
Name: cellfinder-core
Version: 1.0.0
Summary: Automated 3D cell detection in large microscopy images
Author-email: "Adam Tyson, Christian Niedworok, Charly Rousseau" <code@adamltyson.com>
Project-URL: Homepage, https://brainglobe.info
Project-URL: Source Code, https://github.com/brainglobe/cellfinder-core
Project-URL: Bug Tracker, https://github.com/brainglobe/cellfinder-core/issues
Project-URL: Documentation, https://brainglobe.info/documentation/cellfinder/index.html
Classifier: Development Status :: 3 - Alpha
Classifier: Intended Audience :: Developers
Classifier: Intended Audience :: Science/Research
Classifier: Operating System :: OS Independent
Classifier: Programming Language :: Python
Classifier: Programming Language :: Python :: 3.8
Classifier: Programming Language :: Python :: 3.9
Classifier: Programming Language :: Python :: 3.10
Classifier: Topic :: Scientific/Engineering :: Image Recognition
Requires-Python: >=3.8
License-File: LICENSE
Requires-Dist: dask[array]
Requires-Dist: fancylog >=0.0.7
Requires-Dist: brainglobe-utils
Requires-Dist: natsort
Requires-Dist: numba
Requires-Dist: numpy
Requires-Dist: scikit-image
Requires-Dist: scikit-learn
Requires-Dist: tifffile
Requires-Dist: tqdm
Requires-Dist: tensorflow <2.12.0,>=2.5.0 ; platform_system != "Darwin" or platform_machine != "arm64"
Requires-Dist: tensorflow-macos <2.12.0,>=2.5.0 ; platform_system == "Darwin" and platform_machine == "arm64"
Provides-Extra: dev
Requires-Dist: black ; extra == 'dev'
Requires-Dist: gitpython ; extra == 'dev'
Requires-Dist: pre-commit ; extra == 'dev'
Requires-Dist: pyinstrument ; extra == 'dev'
Requires-Dist: pytest ; extra == 'dev'
Requires-Dist: pytest-cov ; extra == 'dev'
Requires-Dist: pytest-lazy-fixture ; extra == 'dev'
Requires-Dist: pytest-mock ; extra == 'dev'
Requires-Dist: pytest-timeout ; extra == 'dev'
Requires-Dist: tox ; extra == 'dev'
